venv_autouse/__init__.py
venv_autouse/common.py
venv_autouse/directory.py
venv_autouse/file.py
venv_autouse/py.typed
venv_autouse-1.0.2.dist-info/METADATA
venv_autouse-1.0.2.dist-info/WHEEL
venv_autouse-1.0.2.dist-info/licenses/LICENSE
venv_autouse-1.0.2.dist-info/RECORD
