Metadata-Version: 2.1
Name: venv-autouse
Version: 1.0.2
Summary: Handling venv for different scripts
Project-URL: Homepage, https://github.com/xonqnopp/python-venv-autouse
Project-URL: Issues, https://github.com/xonqnopp/python-venv-autouse/issues
Author-email: XonqNopp <xonqnoppp@gmail.com>
Maintainer-email: XonqNopp <xonqnoppp@gmail.com>
License: MIT License
License-File: LICENSE
Classifier: License :: OSI Approved :: MIT License
Classifier: Operating System :: OS Independent
Classifier: Programming Language :: Python :: 3
Requires-Python: >=3.10
